ankiapp_batch/__init__.py
ankiapp_batch/__main__.py
ankiapp_batch-0.1.0.dist-info/LICENSE.txt
ankiapp_batch-0.1.0.dist-info/METADATA
ankiapp_batch-0.1.0.dist-info/WHEEL
ankiapp_batch-0.1.0.dist-info/top_level.txt
ankiapp_batch-0.1.0.dist-info/RECORD
