Metadata-Version: 2.1
Name: ankiapp_batch
Version: 0.1.0
Summary: ankiapp_batch
Author-email: Johannes <johannes-programming@posteo.org>
License: The MIT License (MIT)
Project-URL: Download, https://pypi.org/project/ankiapp-batch/#files
Project-URL: Source, https://github.com/johannes-programming/ankiapp_batch
Classifier: License :: OSI Approved :: MIT License
Classifier: Programming Language :: Python
Classifier: Programming Language :: Python :: 3
Requires-Python: >=3.11
License-File: LICENSE.txt
